hctest_install_help/__init__.py
hctest_install_help/install_adb_env/__init__.py
hctest_install_help/install_adb_env/adb_env.py
hctest_install_help/install_adb_env/check_env.py
hctest_install_help/install_adb_env/run.py
hctest_install_help/install_java_env/__init__.py
hctest_install_help/install_java_env/java_env.py
hctest_install_help/install_java_env/run.py
hctest_install_help/package/__init__.py
hctest_install_help/package/mac_env.py
hctest_install_help/package/unzip.py
hctest_install_help/package/windows_env.py
hctest_install_help-1.0.dist-info/METADATA
hctest_install_help-1.0.dist-info/WHEEL
hctest_install_help-1.0.dist-info/top_level.txt
hctest_install_help-1.0.dist-info/RECORD
